scrapely/_htmlpage.pyx
scrapely/tool.py
scrapely/descriptor.py
scrapely/version.py
scrapely/_htmlpage.cpython-311-x86_64-linux-gnu.so
scrapely/template.py
scrapely/_htmlpage.c
scrapely/extractors.py
scrapely/__init__.py
scrapely/htmlpage.py
scrapely/extraction/pageparsing.py
scrapely/extraction/similarity.py
scrapely/extraction/pageobjects.py
scrapely/extraction/regionextract.py
scrapely/extraction/_similarity.c
scrapely/extraction/_similarity.cpython-311-x86_64-linux-gnu.so
scrapely/extraction/__init__.py
scrapely/extraction/_similarity.pyx
sd_scrapely-0.13.5.dist-info/WHEEL
sd_scrapely-0.13.5.dist-info/top_level.txt
sd_scrapely-0.13.5.dist-info/METADATA
sd_scrapely-0.13.5.dist-info/RECORD
sd_scrapely-0.13.5.dist-info/licenses/AUTHORS
