Metadata-Version: 2.4
Name: sd-scrapely
Version: 0.13.5
Summary: A pure-python HTML screen-scraping library
Home-page: https://github.com/SpazioDati/scrapely
Author: Scrapy project
Author-email: Scrapy project <info@scrapy.org>
License-Expression: BSD-3-Clause
Project-URL: Homepage, https://github.com/SpazioDati/scrapely
Project-URL: Repository, https://github.com/SpazioDati/scrapely
Classifier: Development Status :: 5 - Production/Stable
Classifier: Operating System :: OS Independent
Classifier: Programming Language :: Python
Classifier: Programming Language :: Python :: 3
Classifier: Programming Language :: Python :: 3.10
Classifier: Programming Language :: Python :: 3.11
Classifier: Programming Language :: Python :: 3.12
Classifier: Programming Language :: Python :: 3.13
Classifier: Programming Language :: Python :: 3.14
Classifier: Topic :: Internet :: WWW/HTTP
Classifier: Topic :: Text Processing :: Markup :: HTML
Requires-Python: >=3.10
License-File: AUTHORS
Requires-Dist: numpy
Requires-Dist: w3lib
Requires-Dist: cython
Dynamic: author
Dynamic: home-page
Dynamic: license-file
